cryptotensors/__init__.py
cryptotensors/__init__.pyi
cryptotensors/_safetensors_rust.abi3.so
cryptotensors/flax.py
cryptotensors/mlx.py
cryptotensors/numpy.py
cryptotensors/paddle.py
cryptotensors/py.typed
cryptotensors/tensorflow.py
cryptotensors/torch.py
cryptotensors-0.2.0.dist-info/METADATA
cryptotensors-0.2.0.dist-info/WHEEL
cryptotensors-0.2.0.dist-info/licenses/LICENSE
cryptotensors-0.2.0.dist-info/RECORD
