Metadata-Version: 2.4
Name: cryptotensors
Version: 0.2.0
Classifier: Development Status :: 5 - Production/Stable
Classifier: Intended Audience :: Developers
Classifier: Intended Audience :: Education
Classifier: Intended Audience :: Science/Research
Classifier: License :: OSI Approved :: Apache Software License
Classifier: Operating System :: OS Independent
Classifier: Programming Language :: Python :: 3
Classifier: Programming Language :: Python :: 3.7
Classifier: Programming Language :: Python :: 3.8
Classifier: Programming Language :: Python :: 3.9
Classifier: Programming Language :: Python :: 3.10
Classifier: Topic :: Scientific/Engineering :: Artificial Intelligence
Classifier: Typing :: Typed
Requires-Dist: cryptotensors[torch] ; extra == 'all'
Requires-Dist: cryptotensors[numpy] ; extra == 'all'
Requires-Dist: cryptotensors[pinned-tf] ; extra == 'all'
Requires-Dist: cryptotensors[jax] ; extra == 'all'
Requires-Dist: cryptotensors[paddlepaddle] ; extra == 'all'
Requires-Dist: cryptotensors[quality] ; extra == 'all'
Requires-Dist: cryptotensors[testing] ; extra == 'all'
Requires-Dist: cryptotensors[all] ; extra == 'dev'
Requires-Dist: cryptotensors[numpy] ; extra == 'jax'
Requires-Dist: flax>=0.6.3 ; extra == 'jax'
Requires-Dist: jax>=0.3.25 ; extra == 'jax'
Requires-Dist: jaxlib>=0.3.25 ; extra == 'jax'
Requires-Dist: mlx>=0.0.9 ; extra == 'mlx'
Requires-Dist: numpy>=1.21.6 ; extra == 'numpy'
Requires-Dist: cryptotensors[numpy] ; extra == 'paddlepaddle'
Requires-Dist: paddlepaddle>=2.4.1 ; extra == 'paddlepaddle'
Requires-Dist: cryptotensors[numpy] ; extra == 'pinned-tf'
Requires-Dist: tensorflow==2.18.0 ; extra == 'pinned-tf'
Requires-Dist: ruff ; extra == 'quality'
Requires-Dist: cryptotensors[numpy] ; extra == 'tensorflow'
Requires-Dist: tensorflow>=2.11.0 ; extra == 'tensorflow'
Requires-Dist: cryptotensors[numpy] ; extra == 'testing'
Requires-Dist: h5py>=3.7.0 ; extra == 'testing'
Requires-Dist: huggingface-hub>=0.12.1 ; extra == 'testing'
Requires-Dist: setuptools-rust>=1.5.2 ; extra == 'testing'
Requires-Dist: pytest>=7.2.0 ; extra == 'testing'
Requires-Dist: pytest-benchmark>=4.0.0 ; extra == 'testing'
Requires-Dist: hypothesis>=6.70.2 ; extra == 'testing'
Requires-Dist: cryptography>=41.0.0 ; extra == 'testing'
Requires-Dist: cryptotensors[numpy] ; extra == 'testingfree'
Requires-Dist: huggingface-hub>=0.12.1 ; extra == 'testingfree'
Requires-Dist: setuptools-rust>=1.5.2 ; extra == 'testingfree'
Requires-Dist: pytest>=7.2.0 ; extra == 'testingfree'
Requires-Dist: pytest-benchmark>=4.0.0 ; extra == 'testingfree'
Requires-Dist: hypothesis>=6.70.2 ; extra == 'testingfree'
Requires-Dist: packaging ; extra == 'torch'
Requires-Dist: cryptotensors[numpy] ; extra == 'torch'
Requires-Dist: torch>=1.10 ; extra == 'torch'
Provides-Extra: all
Provides-Extra: dev
Provides-Extra: jax
Provides-Extra: mlx
Provides-Extra: numpy
Provides-Extra: paddlepaddle
Provides-Extra: pinned-tf
Provides-Extra: quality
Provides-Extra: tensorflow
Provides-Extra: testing
Provides-Extra: testingfree
Provides-Extra: torch
License-File: LICENSE
Summary: CryptoTensors is an extension of safetensors that adds encryption, signing, and access control (Rego-based policy engine) while maintaining full backward compatibility with the safetensors format
Author-email: Aiyah Meloken <aiyah_meloken@protonmail.com>
Requires-Python: >=3.9
Project-URL: Documentation, https://aiyah-meloken.github.io/cryptotensors/
Project-URL: Homepage, https://github.com/aiyah-meloken/cryptotensors
Project-URL: Source, https://github.com/aiyah-meloken/cryptotensors
